sqlalchemy_singlestoredb/__init__.py
sqlalchemy_singlestoredb/base.py
sqlalchemy_singlestoredb/column.py
sqlalchemy_singlestoredb/ddlelement.py
sqlalchemy_singlestoredb/dtypes.py
sqlalchemy_singlestoredb/reflection.py
sqlalchemy_singlestoredb/tests/__init__.py
sqlalchemy_singlestoredb/tests/test.sql
sqlalchemy_singlestoredb/tests/test_basics.py
sqlalchemy_singlestoredb_backticks_patched-1.1.1.dist-info/LICENSE
sqlalchemy_singlestoredb_backticks_patched-1.1.1.dist-info/METADATA
sqlalchemy_singlestoredb_backticks_patched-1.1.1.dist-info/WHEEL
sqlalchemy_singlestoredb_backticks_patched-1.1.1.dist-info/entry_points.txt
sqlalchemy_singlestoredb_backticks_patched-1.1.1.dist-info/top_level.txt
sqlalchemy_singlestoredb_backticks_patched-1.1.1.dist-info/RECORD
