Metadata-Version: 2.2
Name: sqlalchemy_singlestoredb_backticks_patched
Version: 1.1.1
Summary: SQLAlchemy dialect for the SingleStoreDB database (with backticks patch)
Home-page: https://github.com/singlestore-labs/sqlalchemy-singlestoredb
Author: SingleStore
Author-email: support@singlestore.com
License: Apache-2.0
Classifier: Development Status :: 5 - Production/Stable
Classifier: License :: OSI Approved :: Apache Software License
Classifier: Programming Language :: Python :: 3
Classifier: Programming Language :: Python :: 3 :: Only
Requires-Python: >=3.8
License-File: LICENSE
Requires-Dist: singlestoredb>=1.0.0
Requires-Dist: sqlalchemy<3.0.0dev,>=1.4.0
